{
    "id": 662563,
    "name": "Sillyhouse",
    "author": "xoliverx35",
    "creators": [],
    "verifier": "Simon",
    "verification": "-",
    "percentToQualify": "100",
    "password": "-",
    "records": [
        {
            "user": "xoliverx35",
            "link": "https://www.youtube.com/watch?v=lU-_au3Bv6g",
            "percent": 100
        },
        {
            "user": "PKvime",
            "link": "https://www.youtube.com/watch?v=r6hcE7Jyot8",
            "percent": 100
        },
        {
            "user": "duck",
            "link": "https://www.youtube.com/embed/XHp3FhVHLq8",
            "percent": 100
        },
        {
            "user": "loovigmd",
            "link": "https://medal.tv/games/roblox/clips/jJjCUNG5Mmv9kXdai?invite=cr-MSx6cG0sMjQxMjUxNjQ4LA",
            "percent": 100
        },
                {
            "user": "JoaqFirr",
            "link": "https://youtu.be/LBK4dDGbmkc",
            "percent": 100
        }
    ]
}
